autoclicker/__init__.py
autoclicker/__main__.py
autoclicker/app.py
autoclicker/cli.py
clickmate-0.1.1.dist-info/WHEEL
clickmate-0.1.1.dist-info/entry_points.txt
clickmate-0.1.1.dist-info/METADATA
clickmate-0.1.1.dist-info/RECORD
