Metadata-Version: 2.3
Name: clickmate
Version: 0.1.1
Summary: Add your description here
Keywords: autoclicker,clickmate,automation,macos,quartz,mouse,cli
Author: ivand890
License: MIT License
Classifier: Development Status :: 4 - Beta
Classifier: Intended Audience :: End Users/Desktop
Classifier: Topic :: Utilities
Classifier: License :: OSI Approved :: MIT License
Classifier: Operating System :: MacOS
Classifier: Operating System :: Microsoft :: Windows
Classifier: Operating System :: POSIX :: Linux
Classifier: Programming Language :: Python :: 3
Classifier: Programming Language :: Python :: 3 :: Only
Classifier: Programming Language :: Python :: 3.11
Classifier: Programming Language :: Python :: 3.12
Classifier: Programming Language :: Python :: 3.13
Requires-Dist: pyautogui>=0.9.54
Requires-Dist: pynput>=1.8.1
Requires-Dist: pyobjc-framework-quartz>=10.3 ; sys_platform == 'darwin' and extra == 'mac'
Requires-Python: >=3.11
Project-URL: Changelog, https://github.com/ivand890/autoclicker/releases
Project-URL: Homepage, https://github.com/ivand890/autoclicker
Project-URL: Issues, https://github.com/ivand890/autoclicker/issues
Project-URL: Repository, https://github.com/ivand890/autoclicker
Provides-Extra: mac
